

{"cid":"530","sid":"2045","eventList":[{"eid":325,"et":"African Voices","st":"00:00:00","ed":30},{"eid":328,"et":"CNN Newsroom","st":"00:30:00","ed":30},{"eid":334,"et":"Leading Women/Make, Create, Innovate","st":"01:00:00","ed":30},{"eid":218,"et":"Fareed Zakaria GPS","st":"01:30:00","ed":30},{"eid":219,"et":"Fareed Zakaria GPS","st":"02:00:00","ed":30},{"eid":224,"et":"CNN Newsroom","st":"02:30:00","ed":30},{"eid":62,"et":"World Sport","st":"03:00:00","ed":30},{"eid":65,"et":"CNN Today (with World Sport)","st":"03:30:00","ed":30},{"eid":102,"et":"CNN Today (with World Sport)","st":"04:00:00","ed":30},{"eid":125,"et":"CNN Today (with World Sport)","st":"04:30:00","ed":30},{"eid":769,"et":"CNN Today (with World Sport)","st":"05:00:00","ed":30},{"eid":770,"et":"CNN Today","st":"05:30:00","ed":30},{"eid":771,"et":"World Sport","st":"06:00:00","ed":30},{"eid":566,"et":"Political Mann","st":"06:30:00","ed":30},{"eid":570,"et":"Erin Burnett OutFront","st":"07:00:00","ed":30},{"eid":571,"et":"CNN Marketplace Africa/Make, Create, Innovate","st":"07:30:00","ed":30},{"eid":572,"et":"Amanpour.","st":"08:00:00","ed":30},{"eid":575,"et":"Fareed Zakaria GPS","st":"08:30:00","ed":30},{"eid":716,"et":"Fareed Zakaria GPS","st":"09:00:00","ed":30},{"eid":717,"et":"On China: Dinosaur Discovery","st":"09:30:00","ed":30},{"eid":718,"et":"TBD","st":"10:00:00","ed":30},{"eid":436,"et":"CNN Newsroom (with World Sport)","st":"10:30:00","ed":30},{"eid":440,"et":"CNN Newsroom (with World Sport)","st":"11:00:00","ed":30},{"eid":441,"et":"CNN Newsroom","st":"11:30:00","ed":30},{"eid":442,"et":"CNN Newsroom","st":"12:00:00","ed":30},{"eid":444,"et":"CNN Newsroom","st":"12:30:00","ed":30},{"eid":446,"et":"CNN Newsroom","st":"13:00:00","ed":30},{"eid":634,"et":"CNN Newsroom","st":"13:30:00","ed":30},{"eid":635,"et":"CNN Newsroom","st":"14:00:00","ed":30},{"eid":636,"et":"CNN Newsroom","st":"14:30:00","ed":30},{"eid":708,"et":"Best of Quest","st":"15:00:00","ed":30},{"eid":577,"et":"Political Mann","st":"15:30:00","ed":30},{"eid":582,"et":"African Voices","st":"16:00:00","ed":30},{"eid":758,"et":"The Business View with Nina Dos Santos","st":"16:30:00","ed":30},{"eid":759,"et":"The Business View with Nina Dos Santos","st":"17:00:00","ed":30},{"eid":791,"et":"CNN Newsroom","st":"17:30:00","ed":30},{"eid":317,"et":"World Sport","st":"18:00:00","ed":30},{"eid":50,"et":"News Stream (with World Sport)","st":"18:30:00","ed":30},{"eid":66,"et":"News Stream (with World Sport)","st":"19:00:00","ed":30},{"eid":67,"et":"World Business Today","st":"19:30:00","ed":30},{"eid":68,"et":"World Business Today","st":"20:00:00","ed":30},{"eid":97,"et":"International Desk (with World Sport)","st":"20:30:00","ed":30},{"eid":130,"et":"International Desk (with World Sport)","st":"21:00:00","ed":30},{"eid":131,"et":"Connect the World with Becky Anderson","st":"21:30:00","ed":30},{"eid":148,"et":"Connect the World with Becky Anderson","st":"22:00:00","ed":30},{"eid":166,"et":"International Desk","st":"22:30:00","ed":30},{"eid":455,"et":"International Desk/CNN Marketplace Africa","st":"23:00:00","ed":30},{"eid":456,"et":"Wolf","st":"23:30:00","ed":30}]}
