

{"cid":"533","sid":"2021","eventList":[{"eid":751,"et":"News Live","st":"00:30:00","ed":30},{"eid":753,"et":"Talk to Al Jazeera","st":"01:00:00","ed":30},{"eid":755,"et":"Killing The Messenger","st":"01:30:00","ed":60},{"eid":761,"et":"Newshour","st":"02:30:00","ed":60},{"eid":762,"et":"News Live","st":"03:30:00","ed":30},{"eid":764,"et":"Witness","st":"04:00:00","ed":30},{"eid":64,"et":"Newshour","st":"04:30:00","ed":60},{"eid":65,"et":"News Live","st":"05:30:00","ed":30},{"eid":66,"et":"Inside Story","st":"06:00:00","ed":30},{"eid":67,"et":"Al Jazeera World","st":"06:30:00","ed":60},{"eid":68,"et":"Newshour","st":"07:30:00","ed":60},{"eid":69,"et":"News Live","st":"08:30:00","ed":30},{"eid":70,"et":"TechKnow","st":"09:00:00","ed":30},{"eid":73,"et":"News Live","st":"09:30:00","ed":30},{"eid":108,"et":"Listening Post","st":"10:00:00","ed":30},{"eid":508,"et":"News Live","st":"10:30:00","ed":30},{"eid":509,"et":"101 East","st":"11:00:00","ed":30},{"eid":282,"et":"Head to Head","st":"11:30:00","ed":60},{"eid":414,"et":"News Live","st":"12:30:00","ed":30},{"eid":446,"et":"Inside Story","st":"13:00:00","ed":30},{"eid":370,"et":"News Live","st":"13:30:00","ed":30},{"eid":577,"et":"Earthrise","st":"14:00:00","ed":30},{"eid":804,"et":"News Live","st":"14:30:00","ed":30},{"eid":805,"et":"Witness","st":"15:00:00","ed":30},{"eid":590,"et":"Newshour","st":"15:30:00","ed":60},{"eid":236,"et":"News Live","st":"16:30:00","ed":30},{"eid":649,"et":"Inside Story","st":"17:00:00","ed":30},{"eid":462,"et":"Killing The Messenger","st":"17:30:00","ed":60},{"eid":304,"et":"Newshour","st":"18:30:00","ed":60},{"eid":310,"et":"News Live","st":"19:30:00","ed":30},{"eid":312,"et":"Talk to Al Jazeera","st":"20:00:00","ed":30},{"eid":75,"et":"Newshour","st":"20:30:00","ed":60},{"eid":81,"et":"News Live","st":"21:30:00","ed":30},{"eid":82,"et":"Counting the Cost","st":"22:00:00","ed":30},{"eid":84,"et":"News Live","st":"22:30:00","ed":30},{"eid":85,"et":"Inside Story","st":"23:00:00","ed":30},{"eid":86,"et":"Newshour","st":"23:30:00","ed":60}]}
