

{"cid":"109","sid":"1603","eventList":[{"eid":1082,"et":"Superstar Preview","st":"00:00:00","ed":30},{"eid":1285,"et":"Confessions Of An Indian Teenager","st":"00:30:00","ed":30},{"eid":1001,"et":"Gumrah","st":"01:00:00","ed":60},{"eid":529,"et":"Gumrah","st":"02:00:00","ed":60},{"eid":528,"et":"Sadda Haq - My Life, My Choice","st":"03:00:00","ed":30},{"eid":898,"et":"Swim Team","st":"03:30:00","ed":30},{"eid":903,"et":"Confessions Of An Indian Teenager","st":"04:00:00","ed":30},{"eid":736,"et":"Confessions Of An Indian Teenager","st":"04:30:00","ed":30},{"eid":493,"et":"Sadda Haq - My Life, My Choice","st":"05:00:00","ed":30},{"eid":435,"et":"Swim Team","st":"05:30:00","ed":30},{"eid":441,"et":"Twist Wala Love - Special Fairytales","st":"06:00:00","ed":60},{"eid":459,"et":"Superstar Preview","st":"07:00:00","ed":30},{"eid":535,"et":"Shop India","st":"07:30:00","ed":15},{"eid":127,"et":"Shop India","st":"07:45:00","ed":15},{"eid":483,"et":"Superstar Preview","st":"08:00:00","ed":30},{"eid":61,"et":"Shop India","st":"08:30:00","ed":15},{"eid":164,"et":"Shop India","st":"08:45:00","ed":15},{"eid":1345,"et":"Superstar Preview","st":"09:00:00","ed":30},{"eid":0,"et":"Dare 2 Date","st":"09:30:00","ed":30},{"eid":779,"et":"Confessions Of An Indian Teenager","st":"10:00:00","ed":30},{"eid":35,"et":"Swim Team","st":"10:30:00","ed":30},{"eid":45,"et":"Dil Dosti Dance Dobaara","st":"11:00:00","ed":30},{"eid":189,"et":"Sadda Haq - My Life, My Choice","st":"11:30:00","ed":30},{"eid":205,"et":"Gumrah","st":"12:00:00","ed":60},{"eid":216,"et":"Gumrah","st":"13:00:00","ed":60},{"eid":195,"et":"Gumrah","st":"14:00:00","ed":60},{"eid":690,"et":"Sadda Haq - My Life, My Choice","st":"15:00:00","ed":30},{"eid":717,"et":"Swim Team","st":"15:30:00","ed":30},{"eid":417,"et":"Superstar Preview","st":"16:00:00","ed":30},{"eid":420,"et":"V Best Friends Forever","st":"16:30:00","ed":30},{"eid":316,"et":"Dil Dosti Dance Dobaara","st":"17:00:00","ed":30},{"eid":277,"et":"Secret Diaries - The Hidden Chapters","st":"17:30:00","ed":30},{"eid":289,"et":"Twist Wala Love - Fairy Tales Remixed","st":"18:00:00","ed":30},{"eid":341,"et":"Sadda Haq - My Life, My Choice","st":"18:30:00","ed":30},{"eid":795,"et":"Swim Team","st":"19:00:00","ed":30},{"eid":808,"et":"Dil Dosti Dance Dobaara","st":"19:30:00","ed":30},{"eid":738,"et":"Gumrah","st":"20:00:00","ed":60},{"eid":740,"et":"Swim Team","st":"21:00:00","ed":30},{"eid":179,"et":"Superstar Preview","st":"21:30:00","ed":30},{"eid":65,"et":"Sadda Haq - My Life, My Choice","st":"22:00:00","ed":30},{"eid":1067,"et":"Twist Wala Love - Fairy Tales Remixed","st":"22:30:00","ed":30},{"eid":919,"et":"Gumrah","st":"23:00:00","ed":60}]}
