

{"cid":"121","sid":"2402","eventList":[{"eid":861,"et":"Preview","st":"00:03:00","ed":5},{"eid":326,"et":"Bindass Chillax","st":"00:08:00","ed":3},{"eid":1081,"et":"Preview","st":"00:11:00","ed":4},{"eid":1082,"et":"Bindass Chillax","st":"00:15:00","ed":18},{"eid":1098,"et":"Preview","st":"00:33:00","ed":12},{"eid":1146,"et":"Teleslot","st":"00:45:00","ed":15},{"eid":375,"et":"Teleslot","st":"01:00:00","ed":300},{"eid":572,"et":"Teleslot","st":"06:00:00","ed":45},{"eid":245,"et":"Preview","st":"06:45:00","ed":11},{"eid":342,"et":"Beta Uth Ja","st":"06:56:00","ed":9},{"eid":333,"et":"Dhakka Start","st":"07:05:00","ed":5},{"eid":443,"et":"Preview","st":"07:10:00","ed":5},{"eid":372,"et":"Dhakka Start","st":"07:15:00","ed":8},{"eid":501,"et":"Preview","st":"07:23:00","ed":3},{"eid":319,"et":"Dhakka Start","st":"07:26:00","ed":35},{"eid":565,"et":"Dil Groove Maare","st":"08:01:00","ed":6},{"eid":87,"et":"Preview","st":"08:07:00","ed":6},{"eid":221,"et":"Dil Groove Maare","st":"08:13:00","ed":8},{"eid":89,"et":"Preview","st":"08:21:00","ed":2},{"eid":321,"et":"Dil Groove Maare","st":"08:23:00","ed":35},{"eid":544,"et":"Woofer Phaad Ke","st":"08:58:00","ed":4},{"eid":383,"et":"Preview","st":"09:02:00","ed":5},{"eid":883,"et":"Woofer Phaad Ke","st":"09:07:00","ed":35},{"eid":76,"et":"Preview","st":"09:42:00","ed":3},{"eid":518,"et":"Woofer Phaad Ke","st":"09:45:00","ed":18},{"eid":520,"et":"Preview","st":"10:03:00","ed":4},{"eid":380,"et":"Woofer Phaad Ke","st":"10:07:00","ed":22},{"eid":394,"et":"Tweet Your Beat","st":"10:29:00","ed":26},{"eid":384,"et":"Preview","st":"10:55:00","ed":3},{"eid":385,"et":"Tweet Your Beat","st":"10:58:00","ed":3},{"eid":416,"et":"Bindass Juke Box","st":"11:01:00","ed":41},{"eid":480,"et":"Preview","st":"11:42:00","ed":5},{"eid":1,"et":"Bindass Juke Box","st":"11:47:00","ed":5},{"eid":469,"et":"Preview","st":"11:52:00","ed":6},{"eid":753,"et":"Bindass Juke Box","st":"11:58:00","ed":5},{"eid":914,"et":"Yeh Hai Aashiqui Sun Yaar Try Maar","st":"12:03:00","ed":55},{"eid":417,"et":"Kota Toppers","st":"12:58:00","ed":32},{"eid":138,"et":"Yeh Hai Aashiqui Siyappa Ishq Ka","st":"13:30:00","ed":34},{"eid":663,"et":"Yeh Hai Aashiqui Sun Yaar Try Maar","st":"14:04:00","ed":56},{"eid":396,"et":"Preview","st":"15:00:00","ed":2},{"eid":152,"et":"Teleslot","st":"15:02:00","ed":40},{"eid":215,"et":"Bindass Ekdum Latest","st":"15:42:00","ed":9},{"eid":676,"et":"Preview","st":"15:51:00","ed":2},{"eid":678,"et":"Bindass Ekdum Latest","st":"15:53:00","ed":7},{"eid":960,"et":"Yeh Hai Aashiqui","st":"16:00:00","ed":56},{"eid":8,"et":"Bindass Juke Box","st":"16:56:00","ed":10},{"eid":699,"et":"Preview","st":"17:06:00","ed":5},{"eid":1024,"et":"Bindass Juke Box","st":"17:11:00","ed":7},{"eid":846,"et":"Preview","st":"17:18:00","ed":4},{"eid":1100,"et":"Bindass Juke Box","st":"17:22:00","ed":37},{"eid":7,"et":"Yeh Hai Aashiqui Sun Yaar Try Maar","st":"17:59:00","ed":61},{"eid":777,"et":"Kota Toppers","st":"19:00:00","ed":31},{"eid":17,"et":"Yeh Hai Aashiqui Siyappa Ishq Ka","st":"19:31:00","ed":31},{"eid":1109,"et":"Dil Groove Maare","st":"20:02:00","ed":43},{"eid":1116,"et":"Preview","st":"20:45:00","ed":5},{"eid":1118,"et":"Dil Groove Maare","st":"20:50:00","ed":4},{"eid":892,"et":"Preview","st":"20:54:00","ed":5},{"eid":915,"et":"Dil Groove Maare","st":"20:59:00","ed":3},{"eid":616,"et":"Yeh Hai Aashiqui","st":"21:02:00","ed":58},{"eid":798,"et":"Yeh Hai Aashiqui Sun Yaar Try Maar","st":"22:00:00","ed":57},{"eid":232,"et":"Love By Chance","st":"22:57:00","ed":58},{"eid":940,"et":"Bindass Chillax","st":"23:55:00","ed":7}]}
