

{"cid":"161","sid":"1807","eventList":[{"eid":432,"et":"Kashmir- The land of Divine Love","st":"00:00:00","ed":30},{"eid":438,"et":"Mangal Chowk: Vani Jairam","st":"00:30:00","ed":30},{"eid":441,"et":"Yog Vigyan","st":"01:00:00","ed":14},{"eid":445,"et":"Brick by brick","st":"01:14:00","ed":1},{"eid":246,"et":"The Story on a Red Dot","st":"01:15:00","ed":45},{"eid":668,"et":"Eminent Cartoonist of India - Gopulu","st":"02:00:00","ed":30},{"eid":696,"et":"Sankat Mochan Hanuman","st":"02:30:00","ed":30},{"eid":1035,"et":"Sunita Chaudhary: First Lady Auto Driver","st":"03:00:00","ed":30},{"eid":1043,"et":"Sanskriti Bharati","st":"03:30:00","ed":30},{"eid":751,"et":"Kitabnama","st":"04:00:00","ed":30},{"eid":1001,"et":"The Grand Trunk Road","st":"04:30:00","ed":30},{"eid":166,"et":"Akashwani Sangeet Sammelan","st":"05:00:00","ed":60},{"eid":54,"et":"Trailblazers","st":"06:00:00","ed":30},{"eid":59,"et":"The Treasure Trove of Nature:Assam","st":"06:30:00","ed":30},{"eid":336,"et":"Theatre Director: Salim Arif","st":"07:00:00","ed":30},{"eid":337,"et":"Manipuri Dance by A.Snehasini","st":"07:30:00","ed":30},{"eid":339,"et":"Kashmir- The land of Divine Love","st":"08:00:00","ed":30},{"eid":376,"et":"Mangal Chowk: Vani Jairam","st":"08:30:00","ed":30},{"eid":463,"et":"Yog Vigyan","st":"09:00:00","ed":14},{"eid":464,"et":"Brick by brick","st":"09:14:00","ed":1},{"eid":465,"et":"The Story on a Red Dot","st":"09:15:00","ed":45},{"eid":313,"et":"Eminent Cartoonist of India - Gopulu","st":"10:00:00","ed":30},{"eid":314,"et":"Sankat Mochan Hanuman","st":"10:30:00","ed":30},{"eid":292,"et":"Sunita Chaudhary: First Lady Auto Driver","st":"11:00:00","ed":30},{"eid":295,"et":"Sanskriti Bharati","st":"11:30:00","ed":30},{"eid":496,"et":"Kitabnama","st":"12:00:00","ed":30},{"eid":585,"et":"The Grand Trunk Road","st":"12:30:00","ed":30},{"eid":587,"et":"Akashwani Sangeet Sammelan","st":"13:00:00","ed":60},{"eid":605,"et":"Trailblazers","st":"14:00:00","ed":30},{"eid":606,"et":"The Treasure Trove of Nature:Assam","st":"14:30:00","ed":30},{"eid":621,"et":"Theatre Director: Salim Arif","st":"15:00:00","ed":30},{"eid":504,"et":"Manipuri Dance by A.Snehasini","st":"15:30:00","ed":30},{"eid":629,"et":"Indian Art In Modernism","st":"16:00:00","ed":30},{"eid":630,"et":"Rhythm Of Assam","st":"16:30:00","ed":30},{"eid":639,"et":"Yog Vigyan","st":"17:00:00","ed":30},{"eid":646,"et":"A Question Of Science","st":"17:30:00","ed":30},{"eid":194,"et":"Poet and Critic Satchidanandan Se BaatCh","st":"18:00:00","ed":30},{"eid":241,"et":"Sankat Mochan Hanuman","st":"18:30:00","ed":30},{"eid":242,"et":"Geeta Dharmarajan","st":"19:00:00","ed":30},{"eid":248,"et":"Rang Tarang","st":"19:30:00","ed":30},{"eid":250,"et":"Meri Yaadon Ke Chinar","st":"20:00:00","ed":30},{"eid":705,"et":"Grand Trunk Road","st":"20:30:00","ed":30},{"eid":1041,"et":"Akashwani Sangeet Sammelan","st":"21:00:00","ed":60},{"eid":756,"et":"Wild Adventure","st":"22:00:00","ed":30},{"eid":760,"et":"Mere Desh Ki Dharti","st":"22:30:00","ed":30},{"eid":775,"et":"Munshi Permchand Ki Kahaniyan","st":"23:00:00","ed":30},{"eid":792,"et":"Kathak","st":"23:30:00","ed":30}]}
